[
 {"query": "Farnese Atlas National Museum Naples", "out": "ancient_alchemy/farnese_atlas_naples.jpg", "prefer": "Farnese"},
 {"query": "Greek magical papyri curse text oxyrhynchus", "out": "ancient_alchemy/greek_magical_papyri.jpg", "prefer": "papyri"},
 {"query": "Dendera zodiac ceiling astronomy ancient Egypt", "out": "ancient_alchemy/dendera_ceiling.jpg", "prefer": "Dendera"},
 {"query": "Greco-Roman gem magical inscription cornelian", "out": "ancient_alchemy/gem_inscription.jpg", "prefer": "gem"},
 {"query": "Egyptian bronze mirror ceremonial Ptolemaic", "out": "ancient_alchemy/egyptian_mirror.jpg", "prefer": "mirror"},
 {"query": "Roman bronze vessels Pompeii chemical apparatus", "out": "ancient_alchemy/pompeii_bronze_vessels.jpg", "prefer": "Pompeii"},
 {"query": "Hellenistic astronomicon map celestial coordinates", "out": "ancient_alchemy/hellenistic_astronomicon.jpg", "prefer": "astronomicon"},
 {"query": "Roman gold coins aureus metallurgical analysis", "out": "ancient_alchemy/roman_aureus.jpg", "prefer": "aureus"},
 {"query": "ancient glass vessels Byzantine mosaic color", "out": "ancient_alchemy/ancient_glass_byzantine.jpg", "prefer": "glass"},
 {"query": "Egyptian amulet scarab faience Ptolemaic", "out": "ancient_alchemy/egyptian_scarab.jpg", "prefer": "scarab"},
 {"query": "Roman lead ingots mining metallurgical object", "out": "ancient_alchemy/roman_lead_ingots.jpg", "prefer": "ingot"},
 {"query": "Greek amphora pharmaceutical jar inscription", "out": "ancient_alchemy/greek_amphora_jar.jpg", "prefer": "amphora"},
 {"query": "silver denarius coin assay Roman", "out": "ancient_alchemy/silver_denarius.jpg", "prefer": "denarius"},
 {"query": "Egyptian faience vessel glaze chemistry", "out": "ancient_alchemy/egyptian_faience.jpg", "prefer": "faience"},
 {"query": "Nile river delta city Alexandria harbor", "out": "ancient_alchemy/alexandria_harbor.jpg", "prefer": "Nile"},
 {"query": "Egyptian temple columns Luxor Karnak stone", "out": "ancient_alchemy/luxor_temple.jpg", "prefer": "Luxor"},
 {"query": "Greek bronze mirror back engraved mythological", "out": "ancient_alchemy/greek_bronze_mirror.jpg", "prefer": "engraved"},
 {"query": "Roman purple dye murex shell production", "out": "ancient_alchemy/murex_shell_dye.jpg", "prefer": "murex"},
 {"query": "ancient Egyptian khol eye cosmetic mineral", "out": "ancient_alchemy/egyptian_khol.jpg", "prefer": "khol"},
 {"query": "late Roman glass beads jewelry technique", "out": "ancient_alchemy/roman_glass_beads.jpg", "prefer": "beads"},
 {"query": "Hermes god trade commerce sculpture statue", "out": "ancient_alchemy/hermes_statue.jpg", "prefer": "Hermes statue"},
 {"query": "Zeus Jupiter Roman god sculpture antique", "out": "ancient_alchemy/zeus_jupiter_statue.jpg", "prefer": "Jupiter"},
 {"query": "Mercury god quicksilver alchemy Hermes Trismegistus", "out": "ancient_alchemy/mercury_god.jpg", "prefer": "Mercury"},
 {"query": "Osiris Egyptian god mythology stone relief", "out": "ancient_alchemy/osiris_relief.jpg", "prefer": "Osiris"},
 {"query": "Thoth ibis Egyptian god wisdom writing", "out": "ancient_alchemy/thoth_ibis.jpg", "prefer": "Thoth"},
 {"query": "Roman military camp logistics supply trade route", "out": "ancient_alchemy/roman_military_camp.jpg", "prefer": "camp"},
 {"query": "Greek philosophy stoicism Zeno text scroll", "out": "ancient_alchemy/stoic_philosophy.jpg", "prefer": "stoic"},
 {"query": "Neoplatonism Plotinus philosophy ancient text", "out": "ancient_alchemy/neoplatonism.jpg", "prefer": "Plotinus"},
 {"query": "Egyptian temple priesthood religious hierarchy", "out": "ancient_alchemy/egyptian_priesthood.jpg", "prefer": "priesthood"},
 {"query": "Roman toga patrician citizenship statue", "out": "ancient_alchemy/roman_toga.jpg", "prefer": "toga"},
 {"query": "copper smelting furnace ancient metalwork", "out": "ancient_alchemy/copper_smelting.jpg", "prefer": "copper"},
 {"query": "tin bronze metallurgy ancient Anatolia", "out": "ancient_alchemy/tin_bronze.jpg", "prefer": "tin"},
 {"query": "iron working ancient Celtic blacksmith forge", "out": "ancient_alchemy/iron_forge.jpg", "prefer": "iron"},
 {"query": "silver refining ancient assay parting test", "out": "ancient_alchemy/silver_refining.jpg", "prefer": "silver"},
 {"query": "gold leaf ancient Egyptian costume jewelry technique", "out": "ancient_alchemy/gold_leaf_egyptian.jpg", "prefer": "leaf"},
 {"query": "glass making furnace ancient Roman Sidon Tyre", "out": "ancient_alchemy/glass_furnace_sidon.jpg", "prefer": "furnace"}
]
